{
  "Logics": [
    {
      "x": 329,
      "y": 346,
      "name": "AND",
      "class": "LogicAnd"
    },
    {
      "x": 538,
      "y": 285,
      "name": "TIMER",
      "class": "LogicTimer",
      "current": 79,
      "max": 100
    },
    {
      "x": 264,
      "y": 545,
      "name": "BATTERY",
      "class": "LogicBattery"
    },
    {
      "x": 572,
      "y": 427,
      "name": "TOGGLE",
      "class": "LogicSwitch"
    },
    {
      "x": 581,
      "y": 544,
      "name": "TOGGLE",
      "class": "LogicSwitch"
    }
  ]
}
